setup.py
CsuSort.egg-info/PKG-INFO
CsuSort.egg-info/SOURCES.txt
CsuSort.egg-info/dependency_links.txt
CsuSort.egg-info/requires.txt
CsuSort.egg-info/top_level.txt
Sort/__init__.py
Sort/convert.py
Sort/model.py
Sort/yolo.py
Sort/deep_sort/__init__.py
Sort/deep_sort/detection.py
Sort/deep_sort/iou_matching.py
Sort/deep_sort/kalman_filter.py
Sort/deep_sort/linear_assignment.py
Sort/deep_sort/nn_matching.py
Sort/deep_sort/preprocessing.py
Sort/deep_sort/track.py
Sort/deep_sort/tracker.py
Sort/tools/__init__.py
Sort/tools/freeze_model.py
Sort/tools/generate_detections.py
Sort/yolo3/__init__.py
Sort/yolo3/model.py
Sort/yolo3/utils.py