Metadata-Version: 1.0
Name: CsuSort
Version: 1.0.15
Summary: person or car
Home-page: UNKNOWN
Author: csu_ywj
Author-email: UNKNOWN
License: MIT Licence
Keywords: pip,sort
Platform: any
